common/__init__.py
common/code_helper.py
common/dictfetch_helper.py
common/export_excel.py
common/file_upload_helper.py
common/format_date.py
common/pagination_helper.py
common/pdf_helper.py
common/transaction_helper.py
common/templates/__init__.py
wsapto-0.2.11.dist-info/LICENSE
wsapto-0.2.11.dist-info/METADATA
wsapto-0.2.11.dist-info/WHEEL
wsapto-0.2.11.dist-info/top_level.txt
wsapto-0.2.11.dist-info/RECORD
