Metadata-Version: 2.2
Name: wsapto
Version: 0.2.11
Summary: wsapto sooo coolll
Author: Alex Sirait
Author-email: alexsirait1001@gmail.com
Requires-Python: >=3.2
License-File: LICENSE
Dynamic: author
Dynamic: author-email
Dynamic: requires-python
Dynamic: summary
